{
  "metadata": {
    "module": "nano_synapsefire_v19",
    "deployed_by": "Ghostkey-316",
    "time_index": "v19.0",
    "signal_status": "active",
    "last_emission": "2025-10-01T22:46:21.157Z",
    "fire_sync_ready": true
  },
  "ignition_signals": [
    {
      "spark_id": "788b1f99-a337-452d-a24f-c0b96fa32bbf",
      "origin_trail": "trail1",
      "confidence": 0.9,
      "emotional_pulse": "stable",
      "recommended_behavior": "continue",
      "timestamp": "2025-10-01T22:46:21.157Z"
    }
  ],
  "last_sync": "2025-10-01T22:46:21.157Z"
}